paya-0.1.3.dist-info/METADATA
paya-0.1.3.dist-info/WHEEL
paya.libs/libcrypto-c19c2cf8.so.3
paya.libs/libssl-63597a81.so.3
paya/__init__.py
paya/paya.cpython-312-x86_64-linux-gnu.so
paya-0.1.3.dist-info/RECORD
