Metadata-Version: 2.4
Name: paya
Version: 0.1.3
Classifier: Programming Language :: Rust
Classifier: Programming Language :: Python :: Implementation :: CPython
Classifier: Programming Language :: Python :: Implementation :: PyPy
Summary: A minimum rest client based on deboa http client for rust
Keywords: rest,client,http
Home-Page: https://github.com/ararog/paya
Author-email: Rogerio Pereira Araujo <rogerio.araujo@gmail.com>
License-Expression: MIT
Requires-Python: >=3.8
Project-URL: Github, https://github.com/ararog/paya
